LICENSE.txt
README.md
setup.cfg
setup.py
age_finder.egg-info/PKG-INFO
age_finder.egg-info/SOURCES.txt
age_finder.egg-info/dependency_links.txt
age_finder.egg-info/requires.txt
age_finder.egg-info/top_level.txt
utils/__init__.py
utils/utils.py